{
	"configurations" : 
	[
		{
			"directories" : 
			[
				{
					"build" : ".",
					"jsonFile" : "directory-.-Debug-d0094a50bb2071803777.json",
					"minimumCMakeVersion" : 
					{
						"string" : "3.21"
					},
					"projectIndex" : 0,
					"source" : ".",
					"targetIndexes" : 
					[
						0
					]
				}
			],
			"name" : "Debug",
			"projects" : 
			[
				{
					"directoryIndexes" : 
					[
						0
					],
					"name" : "git_hub",
					"targetIndexes" : 
					[
						0
					]
				}
			],
			"targets" : 
			[
				{
					"directoryIndex" : 0,
					"id" : "git_hub::@6890427a1f51a3e7e1df",
					"jsonFile" : "target-git_hub-Debug-326a0c9c1d06c8c45656.json",
					"name" : "git_hub",
					"projectIndex" : 0
				}
			]
		}
	],
	"kind" : "codemodel",
	"paths" : 
	{
		"build" : "C:/Users/admin/git-hub/cmake-build-debug",
		"source" : "C:/Users/admin/git-hub"
	},
	"version" : 
	{
		"major" : 2,
		"minor" : 3
	}
}
